pyaxonaut/__init__.py
pyaxonaut/config.py
pyaxonaut/constants.py
pyaxonaut/customers.py
pyaxonaut/models/__init__.py
pyaxonaut/models/customer.py
pyaxonaut/tests/__init__.py
pyaxonaut/tests/test_customer_model.py
pyaxonaut/tests/test_customers.py
pyaxonaut-0.0.1.dist-info/LICENSE
pyaxonaut-0.0.1.dist-info/METADATA
pyaxonaut-0.0.1.dist-info/WHEEL
pyaxonaut-0.0.1.dist-info/top_level.txt
pyaxonaut-0.0.1.dist-info/RECORD
