Metadata-Version: 2.1
Name: pyaxonaut
Version: 0.0.1
Summary: A non official API wrapper for Axonaut CRM
Home-page: https://github.com/antoine-briand/pyaxonaut
Author: AJ Innov
Author-email: contact@ajinov.fr
License: UNKNOWN
Platform: UNKNOWN
Classifier: Programming Language :: Python :: 3
Classifier: License :: OSI Approved :: MIT License
Classifier: Operating System :: OS Independent
Requires-Dist: certifi (==2018.11.29)
Requires-Dist: chardet (==3.0.4)
Requires-Dist: coverage (==4.5.2)
Requires-Dist: idna (==2.8)
Requires-Dist: nose (==1.3.7)
Requires-Dist: requests (==2.21.0)
Requires-Dist: urllib3 (==1.24.1)
